kingnest/__init__.py
kingnest/nest.py
kingnest-0.0.9.dist-info/METADATA
kingnest-0.0.9.dist-info/WHEEL
kingnest-0.0.9.dist-info/licenses/LICENSE
kingnest-0.0.9.dist-info/RECORD
