Metadata-Version: 2.1
Name: kingnest
Version: 0.0.9
Summary: A small example nester
Author-email: Ultramax <liuguan@icloud.com>
License-File: LICENSE
Classifier: License :: OSI Approved :: MIT License
Classifier: Operating System :: OS Independent
Classifier: Programming Language :: Python :: 3
Requires-Python: >=3.7
